pyserasa/__init__.py
pyserasa/bloco.py
pyserasa/blocos.py
pyserasa/blocosDados.py
pyserasa/campos.py
pyserasa/crednet.py
pyserasa/erros.py
pyserasa/parserStringDados.py
pyserasa/registrosDados.py
pyserasa/tiposCampos.py
pySerasa-0.1.dist-info/AUTHORS.rst
pySerasa-0.1.dist-info/LICENSE
pySerasa-0.1.dist-info/METADATA
pySerasa-0.1.dist-info/WHEEL
pySerasa-0.1.dist-info/top_level.txt
pySerasa-0.1.dist-info/RECORD
