Metadata-Version: 2.1
Name: pySerasa
Version: 0.1
Summary: Modulo para consulta de string de dados SERASA
Home-page: https://github.com/kmee/pySerasa
Author: KMEE
Author-email: contato@kmee.com.br
License: MIT license
Platform: UNKNOWN
Requires-Dist: requests
Requires-Dist: locales
